MANIFEST.in
README.txt
distribute_setup.py
requirements.txt
setup.py
test-requirements.txt
Gluttony.egg-info/PKG-INFO
Gluttony.egg-info/SOURCES.txt
Gluttony.egg-info/dependency_links.txt
Gluttony.egg-info/entry_points.txt
Gluttony.egg-info/requires.txt
Gluttony.egg-info/top_level.txt
gluttony/__init__.py
gluttony/commands.py
gluttony/dependency.py
gluttony/version.py