Metadata-Version: 1.0
Name: Gluttony
Version: 0.8
Summary: A tool for find dependencies relationships between Python packages
Home-page: http://github.com/victorlin/gluttony
Author: Victor Lin
Author-email: bornstub@gmail.com
License: MIT
Keywords: package dependency relationship
Platform: UNKNOWN
